pyniverse/ZooniverseClassifications.py
pyniverse/__init__.py
pyniverse-1.0.0.data/scripts/zooniverse-classifications-analyse.py
pyniverse-1.0.0.dist-info/LICENSE
pyniverse-1.0.0.dist-info/METADATA
pyniverse-1.0.0.dist-info/WHEEL
pyniverse-1.0.0.dist-info/top_level.txt
pyniverse-1.0.0.dist-info/RECORD
