Metadata-Version: 2.1
Name: pyniverse
Version: 1.0.0
Home-page: https://github.com/philipwfowler/pyniverse
Author: Philip W Fowler
License: MIT
License-File: LICENSE
Requires-Dist: numpy (>=1.13)
Requires-Dist: pandas (>=0.21.0)
Requires-Dist: tqdm (>=4.19)
Requires-Dist: ujson (>=1.35)
Requires-Dist: matplotlib (>=2.1.1)
